mkdv/__init__.py
mkdv/__main__.py
mkdv/cmd_files.py
mkdv/cmd_filespec.py
mkdv/cmd_list.py
mkdv/cmd_regress.py
mkdv/cmd_run.py
mkdv/core_manager_w.py
mkdv/coredb_mgr.py
mkdv/generator_spec.py
mkdv/job_count_expander.py
mkdv/job_limit_spec.py
mkdv/job_queue.py
mkdv/job_queue_builder.py
mkdv/job_queue_set.py
mkdv/job_runner.py
mkdv/job_selector.py
mkdv/job_spec.py
mkdv/job_spec_filter.py
mkdv/job_spec_gen.py
mkdv/job_spec_gen_loader.py
mkdv/job_spec_set.py
mkdv/job_vars.py
mkdv/job_yaml_reader.py
mkdv/job_yaml_writer.py
mkdv/jobspec_loader.py
mkdv/mkdv_py.py
mkdv/mkdv_yaml_composer.py
mkdv/mkdv_yaml_parser.py
mkdv/plugin_mgr.py
mkdv/stream_provider.py
mkdv/yaml_loader.py
mkdv/backends/__init__.py
mkdv/backends/backend.py
mkdv/backends/backend_local.py
mkdv/backends/backend_lsf.py
mkdv/backends/backend_slurm.py
mkdv/generators/__init__.py
mkdv/generators/generator.py
mkdv/parser/__init__.py
mkdv/parser/default.py
mkdv/runners/allure_reporter.py
mkdv/runners/runner.py
mkdv/runners/runner_gtest.py
mkdv/runners/runner_make.py
mkdv/runners/runner_pypyr.py
mkdv/runners/runner_python.py
mkdv/runners/runner_rgy.py
mkdv/runners/runner_spec.py
mkdv/share/mkfiles/dv.mk
mkdv/share/mkfiles/mkdv_cocotb.mk
mkdv/share/mkfiles/mkdv_icarus.mk
mkdv/share/mkfiles/mkdv_icestorm.mk
mkdv/share/mkfiles/mkdv_ncsim.mk
mkdv/share/mkfiles/mkdv_none.mk
mkdv/share/mkfiles/mkdv_openlane.mk
mkdv/share/mkfiles/mkdv_pybfms.mk
mkdv/share/mkfiles/mkdv_quartus.mk
mkdv/share/mkfiles/mkdv_questa.mk
mkdv/share/mkfiles/mkdv_sby.mk
mkdv/share/mkfiles/mkdv_vcs.mk
mkdv/share/mkfiles/mkdv_vlsim.mk
mkdv/share/mkfiles/tool_unknown.mk
mkdv/steps/__init__.py
mkdv/steps/common_hdl_build.py
mkdv/steps/common_hdl_run.py
mkdv/steps/entry.py
mkdv/steps/filespec.py
mkdv/steps/pyrun.py
mkdv/tasks/__init__.py
mkdv/tools/__init__.py
mkdv/tools/tool_rgy.py
mkdv/tools/tool_utils.py
mkdv/tools/hdl/__init__.py
mkdv/tools/hdl/hdl_tool.py
mkdv/tools/hdl/hdl_tool_config.py
mkdv/tools/hdl/hdl_tool_mgr.py
mkdv-0.0.1.6674108495.dist-info/LICENSE
mkdv-0.0.1.6674108495.dist-info/METADATA
mkdv-0.0.1.6674108495.dist-info/WHEEL
mkdv-0.0.1.6674108495.dist-info/entry_points.txt
mkdv-0.0.1.6674108495.dist-info/top_level.txt
mkdv-0.0.1.6674108495.dist-info/RECORD
