Metadata-Version: 2.1
Name: mkdv
Version: 0.0.1.6674108495
Summary: mkdv is a Makefile-based mechanism for running Design Verification tools with a Python regression runner
Home-page: https://github.com/fvutils/mkdv
Author: Matthew Ballance
Author-email: matt.ballance@gmail.com
License: Apache 2.0
Keywords: Python,Functional Verification
License-File: LICENSE
Requires-Dist: allure-python-commons
Requires-Dist: colorama
Requires-Dist: fusesoc
Requires-Dist: jsonschema
Requires-Dist: markdown
Requires-Dist: pypyr >=5.3.0
Requires-Dist: pyyaml
Requires-Dist: toposort
